cursofiap/__init__.py
cursofiap/core.py
teste_upload_1kawanxavier-1.0.0.dist-info/METADATA
teste_upload_1kawanxavier-1.0.0.dist-info/WHEEL
teste_upload_1kawanxavier-1.0.0.dist-info/top_level.txt
teste_upload_1kawanxavier-1.0.0.dist-info/RECORD
